flo/__init__.py
flo/exceptions.py
flo/review.py
flo/buildium/__init__.py
flo/buildium/client.py
flo/buildium/models.py
flo/datasets/__init__.py
flo/datasets/client.py
flo/datasets/exceptions.py
flo/datasets/models.py
flo/hostaway/__init__.py
flo/hostaway/client.py
flo/hostaway/models.py
flo/jobber/__init__.py
flo/jobber/client.py
flo/jobber/models.py
flo/merge/__init__.py
flo/merge/client.py
flo/merge/models.py
flo/plaid/__init__.py
flo/plaid/client.py
flo/plaid/models.py
flo/quickbooks/__init__.py
flo/quickbooks/client.py
flo/quickbooks/models.py
flo/rent_manager/__init__.py
flo/rent_manager/client.py
flo/rent_manager/models.py
flo/review/__init__.py
flo/review/client.py
flo_sdk-0.9.4.dist-info/METADATA
flo_sdk-0.9.4.dist-info/WHEEL
flo_sdk-0.9.4.dist-info/top_level.txt
flo_sdk-0.9.4.dist-info/RECORD
