Metadata-Version: 2.4
Name: flo-sdk
Version: 0.9.4
Summary: Python SDK for Flo workflows - datasets, integrations, and workflow utilities
Author: Flo
Classifier: Development Status :: 3 - Alpha
Classifier: Intended Audience :: Developers
Classifier: License :: OSI Approved :: MIT License
Classifier: Programming Language :: Python :: 3
Classifier: Programming Language :: Python :: 3.11
Requires-Python: >=3.11
Requires-Dist: requests==2.31.0
Requires-Dist: python-dateutil<3.0.0,>=2.8.2
Requires-Dist: tenacity==8.2.3
Requires-Dist: plaid-python==11.6.0
Requires-Dist: pandas==2.1.4
Requires-Dist: openpyxl==3.1.2
Requires-Dist: xlrd==2.0.1
Requires-Dist: httpx==0.25.2
Requires-Dist: pydantic==2.5.3
Requires-Dist: python-dotenv==1.0.0
Requires-Dist: MergePythonClient>=1.0.0
